coolutils/__init__.py
coolutils/coolutils.py
utilscool-1.0.0.dist-info/LICENSE
utilscool-1.0.0.dist-info/METADATA
utilscool-1.0.0.dist-info/WHEEL
utilscool-1.0.0.dist-info/top_level.txt
utilscool-1.0.0.dist-info/RECORD
