Metadata-Version: 2.1
Name: utilscool
Version: 1.0.0
Summary: A cool utility library
Home-page: https://github.com/TitanStar73/coolutils
Author: TitanStar73
Author-email: 
Project-URL: Source, https://github.com/TitanStar73/coolutils
Classifier: Programming Language :: Python :: 3
Classifier: License :: OSI Approved :: Apache Software License
Classifier: Operating System :: OS Independent
Requires-Python: >=3.6
License-File: LICENSE
